la_deep_get/__init__.py
la_deep_get-0.0.6.dist-info/WHEEL
la_deep_get-0.0.6.dist-info/METADATA
la_deep_get-0.0.6.dist-info/license_files/LICENSE
la_deep_get-0.0.6.dist-info/RECORD
